cdk_cloudformation_netapp_fsxn_svmpeer/__init__.py
cdk_cloudformation_netapp_fsxn_svmpeer/py.typed
cdk_cloudformation_netapp_fsxn_svmpeer/_jsii/__init__.py
cdk_cloudformation_netapp_fsxn_svmpeer/_jsii/netapp-fsxn-svmpeer@1.0.0-alpha.7.jsii.tgz
cdk_cloudformation_netapp_fsxn_svmpeer-1.0.0a7.dist-info/LICENSE
cdk_cloudformation_netapp_fsxn_svmpeer-1.0.0a7.dist-info/METADATA
cdk_cloudformation_netapp_fsxn_svmpeer-1.0.0a7.dist-info/WHEEL
cdk_cloudformation_netapp_fsxn_svmpeer-1.0.0a7.dist-info/top_level.txt
cdk_cloudformation_netapp_fsxn_svmpeer-1.0.0a7.dist-info/RECORD
